<?xml version='1.0'?>
<!DOCTYPE platform SYSTEM "http://simgrid.gforge.inria.fr/simgrid/simgrid.dtd">
<platform version="4.1">
	<actor host="Sensor-0" function="sensor">
	</actor>
	<actor host="Sensor-1" function="sensor">
	</actor>
	<actor host="Sensor-2" function="sensor">
	</actor>
	<actor host="Sensor-3" function="sensor">
	</actor>
	<actor host="Sensor-4" function="sensor">
	</actor>
	<actor host="Sensor-5" function="sensor">
	</actor>
	<actor host="Sensor-6" function="sensor">
	</actor>
	<actor host="Sensor-7" function="sensor">
	</actor>
	<actor host="Sensor-8" function="sensor">
	</actor>
	<actor host="Sensor-9" function="sensor">
	</actor>
	<actor host="Sensor-10" function="sensor">
	</actor>
	<actor host="Sensor-11" function="sensor">
	</actor>
	<actor host="Sensor-12" function="sensor">
	</actor>
	<actor host="Sensor-13" function="sensor">
	</actor>
	<actor host="Msq_node-0" function="msq_node">
	</actor>
	<actor host="Msq_node-1" function="msq_node">
	</actor>
	<actor host="Msq_node-2" function="msq_node">
	</actor>
	<actor host="Msq_node-3" function="msq_node">
	</actor>
	<actor host="Msq_node-4" function="msq_node">
	</actor>
	<actor host="Msq_node-5" function="msq_node">
	</actor>
	<actor host="Msq_node-6" function="msq_node">
	</actor>
	<actor host="Msq_node-7" function="msq_node">
	</actor>
	<actor host="Msq_node-8" function="msq_node">
	</actor>
	<actor host="Msq_node-9" function="msq_node">
	</actor>
	<actor host="Msq_node-10" function="msq_node">
	</actor>
	<actor host="Msq_node-11" function="msq_node">
	</actor>
	<actor host="Msq_node-12" function="msq_node">
	</actor>
	<actor host="Msq_node-13" function="msq_node">
	</actor>

</platform>